{
  "model/navigation.json": 1622897325196,
  "controller/App.controller.js": 1627136320215,
  "i18n/i18n.properties": 1622940419297,
  "pwa-manifest.json": 1622897578689,
  "manifest.json": 1627136320111,
  "controller/util/SWHelper.js": 1627136320503,
  "controller/util/BaseController.js": 1627136320419,
  "controller/Home.controller.js": 1627136320315,
  "model/prompt.json": 1622940415205,
  "sw.js": 1622706858092,
  "Component.js": 1627136319911,
  "Component-preload.js": 1627136395048,
  "controller/Home-dbg.controller.js": 1627136320315,
  "controller/util/BaseController-dbg.js": 1627136320419,
  "controller/util/SWHelper-dbg.js": 1627136320503,
  "controller/App-dbg.controller.js": 1627136320215,
  "sw-dbg.js": 1622706858092,
  "Component-dbg.js": 1627136319911,
  "sap-ui-cachebuster-info.json": 1627136395180,
  "view/Home.view.xml": 1627136317531,
  "view/App.view.xml": 1627136320555,
  "images/icon.png": 1622897304382,
  "index.html": 1627136320007
}